torchassistant/__init__.py
torchassistant/adapters.py
torchassistant/collators.py
torchassistant/data.py
torchassistant/exceptions.py
torchassistant/formatters.py
torchassistant/loss_functions.py
torchassistant/metrics.py
torchassistant/output_adapters.py
torchassistant/output_devices.py
torchassistant/preprocessors.py
torchassistant/processing_graph.py
torchassistant/stop_conditions.py
torchassistant/training.py
torchassistant/transforms.py
torchassistant/utils.py
torchassistant/cmd_api/__init__.py
torchassistant/cmd_api/evaluate.py
torchassistant/cmd_api/infer.py
torchassistant/cmd_api/init.py
torchassistant/cmd_api/train.py
torchassistant/session/__init__.py
torchassistant/session/data_classes.py
torchassistant/session/override_spec.py
torchassistant/session/registry.py
torchassistant/session/parse/__init__.py
torchassistant/session/parse/loaders.py
torchassistant-0.2.1.dist-info/METADATA
torchassistant-0.2.1.dist-info/WHEEL
torchassistant-0.2.1.dist-info/entry_points.txt
torchassistant-0.2.1.dist-info/license_files/LICENSE
torchassistant-0.2.1.dist-info/RECORD
