Metadata-Version: 2.1
Name: torchassistant
Version: 0.2.1
Summary: A deep learning framework and automation tool built on top of PyTorch
Project-URL: Documentation, https://github.com/X-rayLaser/TorchAssistant/wiki
Project-URL: Homepage, https://github.com/X-rayLaser/TorchAssistant
Author-email: Evgenii Dolotov <supernovaprotocol@gmail.com>
Keywords: deep-learning,machine-learning,pytorch
Classifier: Intended Audience :: Developers
Classifier: Intended Audience :: Science/Research
Classifier: License :: OSI Approved :: MIT License
Classifier: Operating System :: OS Independent
Classifier: Programming Language :: Python :: 3
Classifier: Topic :: Scientific/Engineering
Classifier: Topic :: Scientific/Engineering :: Artificial Intelligence
Classifier: Topic :: Scientific/Engineering :: Mathematics
Classifier: Topic :: Software Development
Classifier: Topic :: Software Development :: Libraries
Classifier: Topic :: Software Development :: Libraries :: Python Modules
Classifier: Topic :: Utilities
Requires-Python: >=3.6.9
Requires-Dist: pillow<10,>=8.4.0
